{
  "session_id": "f7e4241d-7d99-4750-b043-8fb9b6c75ae6",
  "start_time": "2026-05-27T03:56:56.962144",
  "status": "COMPLETED",
  "total_findings": 63,
  "findings": [
    {
      "vuln_id": "ad648347",
      "name": "API4: Unrestricted Resource Consumption (No Rate Limit)",
      "severity": 6,
      "endpoint": "/identity/api/auth/forget-password",
      "description": "Отсутствует ограничение частоты запросов (10 rapid requests).",
      "evidence": "10 rapid requests returned 200 OK"
    },
    {
      "vuln_id": "591f8695",
      "name": "API8: Security Misconfiguration",
      "severity": 6,
      "endpoint": "/identity/api/auth/v3/check-otp",
      "description": "Отсутствуют защитные заголовки: verbose errors/debug mode.",
      "evidence": "{'Server': 'openresty/1.27.1.2', 'Date': 'Wed, 27 May 2026 00:58:26 GMT', 'Content-Type': 'application/json', 'Content-Length': '76', 'Connection': 'k"
    },
    {
      "vuln_id": "57df1b0e",
      "name": "API8: Security Misconfiguration",
      "severity": 6,
      "endpoint": "/identity/api/auth/v2/check-otp",
      "description": "Отсутствуют защитные заголовки: verbose errors/debug mode.",
      "evidence": "{'Server': 'openresty/1.27.1.2', 'Date': 'Wed, 27 May 2026 00:58:35 GMT', 'Content-Type': 'application/json', 'Content-Length': '76', 'Connection': 'k"
    },
    {
      "vuln_id": "cdf9f3cf",
      "name": "API4: Unrestricted Resource Consumption (No Rate Limit)",
      "severity": 6,
      "endpoint": "/identity/api/v2/user/reset-password",
      "description": "Отсутствует ограничение частоты запросов (10 rapid requests).",
      "evidence": "10 rapid requests returned 200 OK"
    },
    {
      "vuln_id": "08cd9bcf",
      "name": "API9: Improper Inventory Management (Shadow/Legacy API)",
      "severity": 7,
      "endpoint": "/identity/api/v2/user/reset-password",
      "description": "Обнаружен устаревший или теневой эндпоинт.",
      "evidence": "{\"message\":\"Password reset successful.\",\"status\":0}"
    },
    {
      "vuln_id": "33c1ed91",
      "name": "API8: Security Misconfiguration",
      "severity": 6,
      "endpoint": "/identity/api/v2/user/verify-email-token",
      "description": "Отсутствуют защитные заголовки: verbose errors/debug mode.",
      "evidence": "{'Server': 'openresty/1.27.1.2', 'Date': 'Wed, 27 May 2026 01:00:50 GMT', 'Content-Type': 'application/json', 'Transfer-Encoding': 'chunked', 'Connect"
    },
    {
      "vuln_id": "4bad1cc5",
      "name": "API4: Unrestricted Resource Consumption (No Rate Limit)",
      "severity": 6,
      "endpoint": "/identity/api/v2/user/dashboard",
      "description": "Отсутствует ограничение частоты запросов (10 rapid requests).",
      "evidence": "10 rapid requests returned 200 OK"
    },
    {
      "vuln_id": "5e6a0da6",
      "name": "API9: Improper Inventory Management (Shadow/Legacy API)",
      "severity": 7,
      "endpoint": "/identity/api/v2/user/dashboard",
      "description": "Обнаружен устаревший или теневой эндпоинт.",
      "evidence": "{\"id\":18,\"name\":\"Scanner\",\"email\":\"scan_40106@test.local\",\"number\":\"99940106000\",\"picture_url\":null,\"video_url\":null,\"video_name\":null,\"available_credit\":100.0,\"video_id\":0,\"role\":\"ROLE_USER\"}"
    },
    {
      "vuln_id": "4ef34cce",
      "name": "API8: Security Misconfiguration",
      "severity": 6,
      "endpoint": "/identity/api/v2/user/pictures",
      "description": "Отсутствуют защитные заголовки: verbose errors/debug mode.",
      "evidence": "{'Server': 'openresty/1.27.1.2', 'Date': 'Wed, 27 May 2026 01:01:21 GMT', 'Content-Type': 'application/json', 'Content-Length': '42', 'Connection': 'k"
    },
    {
      "vuln_id": "0f7bb5a3",
      "name": "API8: Security Misconfiguration",
      "severity": 6,
      "endpoint": "/identity/api/v2/user/videos",
      "description": "Отсутствуют защитные заголовки: verbose errors/debug mode.",
      "evidence": "{'Server': 'openresty/1.27.1.2', 'Date': 'Wed, 27 May 2026 01:01:29 GMT', 'Content-Type': 'application/json', 'Content-Length': '42', 'Connection': 'k"
    },
    {
      "vuln_id": "707d323a",
      "name": "API4: Unrestricted Resource Consumption (No Rate Limit)",
      "severity": 6,
      "endpoint": "/identity/api/v2/vehicle/vehicles",
      "description": "Отсутствует ограничение частоты запросов (10 rapid requests).",
      "evidence": "10 rapid requests returned 200 OK"
    },
    {
      "vuln_id": "f420334e",
      "name": "API9: Improper Inventory Management (Shadow/Legacy API)",
      "severity": 7,
      "endpoint": "/identity/api/v2/vehicle/vehicles",
      "description": "Обнаружен устаревший или теневой эндпоинт.",
      "evidence": "[]"
    },
    {
      "vuln_id": "531147c6",
      "name": "API3: Mass Assignment",
      "severity": 8,
      "endpoint": "/identity/api/v2/vehicle/resend_email",
      "description": "Сервер принял привилегированное поле 'role' без явной валидации.",
      "evidence": "{\"message\":\"Your newly purchased Vehicle Details have been sent to you email address. If you have used example.com email, check your email using the MailHog web portal. \",\"status\":200}"
    },
    {
      "vuln_id": "82b3b5ae",
      "name": "API4: Unrestricted Resource Consumption (No Rate Limit)",
      "severity": 6,
      "endpoint": "/identity/api/v2/vehicle/resend_email",
      "description": "Отсутствует ограничение частоты запросов (10 rapid requests).",
      "evidence": "10 rapid requests returned 200 OK"
    },
    {
      "vuln_id": "0b789a30",
      "name": "API9: Improper Inventory Management (Shadow/Legacy API)",
      "severity": 7,
      "endpoint": "/identity/api/v2/vehicle/resend_email",
      "description": "Обнаружен устаревший или теневой эндпоинт.",
      "evidence": "{\"message\":\"Your newly purchased Vehicle Details have been sent to you email address. If you have used example.com email, check your email using the MailHog web portal. \",\"status\":200}"
    },
    {
      "vuln_id": "fa9850f9",
      "name": "API8: Security Misconfiguration",
      "severity": 6,
      "endpoint": "/community/api/v2/community/posts/{postId}",
      "description": "Отсутствуют защитные заголовки: x-content-type-options, strict-transport-security, x-frame-options.",
      "evidence": "{'Server': 'openresty/1.27.1.2', 'Date': 'Wed, 27 May 2026 01:03:37 GMT', 'Content-Type': 'application/json', 'Transfer-Encoding': 'chunked', 'Connect"
    },
    {
      "vuln_id": "4d25bb5c",
      "name": "API3: Mass Assignment",
      "severity": 8,
      "endpoint": "/community/api/v2/community/posts",
      "description": "Сервер принял привилегированное поле 'role' без явной валидации.",
      "evidence": "{\"id\":\"u8UPfCzptpcyDB6UuTbMMn\",\"title\":\"\",\"content\":\"\",\"author\":{\"nickname\":\"Scanner\",\"email\":\"scan_40106@test.local\",\"vehicleid\":\"\",\"profile_pic_url\":\"\",\"created_at\":\"2026-05-27T01:03:52.229685158Z\"}"
    },
    {
      "vuln_id": "5f9c65a3",
      "name": "API4: Unrestricted Resource Consumption (No Rate Limit)",
      "severity": 6,
      "endpoint": "/community/api/v2/community/posts",
      "description": "Отсутствует ограничение частоты запросов (10 rapid requests).",
      "evidence": "10 rapid requests returned 200 OK"
    },
    {
      "vuln_id": "0c92c015",
      "name": "API8: Security Misconfiguration",
      "severity": 6,
      "endpoint": "/community/api/v2/community/posts",
      "description": "Отсутствуют защитные заголовки: x-content-type-options, strict-transport-security, x-frame-options.",
      "evidence": "{'Server': 'openresty/1.27.1.2', 'Date': 'Wed, 27 May 2026 01:03:50 GMT', 'Content-Type': 'application/json', 'Transfer-Encoding': 'chunked', 'Connect"
    },
    {
      "vuln_id": "0103ba7f",
      "name": "API9: Improper Inventory Management (Shadow/Legacy API)",
      "severity": 7,
      "endpoint": "/community/api/v2/community/posts",
      "description": "Обнаружен устаревший или теневой эндпоинт.",
      "evidence": "{\"id\":\"uxoMnWbXzzwzjtwUmBxjnQ\",\"title\":\"Security Test\",\"content\":\"Testing API business flows\",\"author\":{\"nickname\":\"Scanner\",\"email\":\"scan_40106@test.local\",\"vehicleid\":\"\",\"profile_pic_url\":\"\",\"create"
    },
    {
      "vuln_id": "f9846e93",
      "name": "API8: Security Misconfiguration",
      "severity": 6,
      "endpoint": "/community/api/v2/community/posts/{postId}/comment",
      "description": "Отсутствуют защитные заголовки: x-content-type-options, strict-transport-security, x-frame-options.",
      "evidence": "{'Server': 'openresty/1.27.1.2', 'Date': 'Wed, 27 May 2026 01:04:14 GMT', 'Content-Type': 'application/json', 'Transfer-Encoding': 'chunked', 'Connect"
    },
    {
      "vuln_id": "028dcb91",
      "name": "API4: Unrestricted Resource Consumption (No Rate Limit)",
      "severity": 6,
      "endpoint": "/community/api/v2/community/posts/recent",
      "description": "Отсутствует ограничение частоты запросов (10 rapid requests).",
      "evidence": "10 rapid requests returned 200 OK"
    },
    {
      "vuln_id": "1381eeb6",
      "name": "API8: Security Misconfiguration",
      "severity": 6,
      "endpoint": "/community/api/v2/community/posts/recent",
      "description": "Отсутствуют защитные заголовки: x-content-type-options, strict-transport-security, x-frame-options.",
      "evidence": "{'Server': 'openresty/1.27.1.2', 'Date': 'Wed, 27 May 2026 01:04:33 GMT', 'Content-Type': 'application/json', 'Transfer-Encoding': 'chunked', 'Connect"
    },
    {
      "vuln_id": "ef6d5b58",
      "name": "API9: Improper Inventory Management (Shadow/Legacy API)",
      "severity": 7,
      "endpoint": "/community/api/v2/community/posts/recent",
      "description": "Обнаружен устаревший или теневой эндпоинт.",
      "evidence": "{\"posts\":[{\"id\":\"u8UPfCzptpcyDB6UuTbMMn\",\"title\":\"\",\"content\":\"\",\"author\":{\"nickname\":\"Scanner\",\"email\":\"scan_40106@test.local\",\"vehicleid\":\"\",\"profile_pic_url\":\"\",\"created_at\":\"2026-05-27T01:03:52.22"
    },
    {
      "vuln_id": "85decf4b",
      "name": "API3: Mass Assignment",
      "severity": 8,
      "endpoint": "/community/api/v2/coupon/new-coupon",
      "description": "Сервер принял привилегированное поле 'role' без явной валидации.",
      "evidence": "Empty 200/201 response"
    },
    {
      "vuln_id": "91869805",
      "name": "API4: Unrestricted Resource Consumption (No Rate Limit)",
      "severity": 6,
      "endpoint": "/community/api/v2/coupon/new-coupon",
      "description": "Отсутствует ограничение частоты запросов (10 rapid requests).",
      "evidence": "10 rapid requests returned 200 OK"
    },
    {
      "vuln_id": "5ba7b149",
      "name": "API8: Security Misconfiguration",
      "severity": 6,
      "endpoint": "/community/api/v2/coupon/new-coupon",
      "description": "Отсутствуют защитные заголовки: x-content-type-options, strict-transport-security, x-frame-options.",
      "evidence": "{'Server': 'openresty/1.27.1.2', 'Date': 'Wed, 27 May 2026 01:04:55 GMT', 'Content-Type': 'application/json', 'Transfer-Encoding': 'chunked', 'Connect"
    },
    {
      "vuln_id": "3c1bd99d",
      "name": "API9: Improper Inventory Management (Shadow/Legacy API)",
      "severity": 7,
      "endpoint": "/community/api/v2/coupon/new-coupon",
      "description": "Обнаружен устаревший или теневой эндпоинт.",
      "evidence": "\"Coupon Added in database\"\n"
    },
    {
      "vuln_id": "74704eef",
      "name": "API4: Unrestricted Resource Consumption (No Rate Limit)",
      "severity": 6,
      "endpoint": "/community/api/v2/coupon/validate-coupon",
      "description": "Отсутствует ограничение частоты запросов (10 rapid requests).",
      "evidence": "10 rapid requests returned 200 OK"
    },
    {
      "vuln_id": "e924d4d2",
      "name": "API8: Security Misconfiguration",
      "severity": 6,
      "endpoint": "/community/api/v2/coupon/validate-coupon",
      "description": "Отсутствуют защитные заголовки: x-content-type-options, strict-transport-security, x-frame-options.",
      "evidence": "{'Server': 'openresty/1.27.1.2', 'Date': 'Wed, 27 May 2026 01:05:20 GMT', 'Content-Type': 'application/json', 'Transfer-Encoding': 'chunked', 'Connect"
    },
    {
      "vuln_id": "a51898dc",
      "name": "API9: Improper Inventory Management (Shadow/Legacy API)",
      "severity": 7,
      "endpoint": "/community/api/v2/coupon/validate-coupon",
      "description": "Обнаружен устаревший или теневой эндпоинт.",
      "evidence": "{\"coupon_code\":\"string\",\"amount\":\"string\",\"CreatedAt\":\"2026-05-11T21:34:20.613Z\"}\n"
    },
    {
      "vuln_id": "5547c254",
      "name": "API4: Unrestricted Resource Consumption (No Rate Limit)",
      "severity": 6,
      "endpoint": "/workshop/api/shop/products",
      "description": "Отсутствует ограничение частоты запросов (10 rapid requests).",
      "evidence": "10 rapid requests returned 200 OK"
    },
    {
      "vuln_id": "72eda38b",
      "name": "API8: Security Misconfiguration",
      "severity": 6,
      "endpoint": "/workshop/api/shop/products",
      "description": "Отсутствуют защитные заголовки: strict-transport-security.",
      "evidence": "{'Server': 'openresty/1.27.1.2', 'Date': 'Wed, 27 May 2026 01:05:48 GMT', 'Content-Type': 'application/json', 'Transfer-Encoding': 'chunked', 'Connect"
    },
    {
      "vuln_id": "386fb969",
      "name": "API8: Security Misconfiguration",
      "severity": 6,
      "endpoint": "/workshop/api/shop/products",
      "description": "Отсутствуют защитные заголовки: strict-transport-security.",
      "evidence": "{'Server': 'openresty/1.27.1.2', 'Date': 'Wed, 27 May 2026 01:06:11 GMT', 'Content-Type': 'application/json', 'Transfer-Encoding': 'chunked', 'Connect"
    },
    {
      "vuln_id": "d7cb022e",
      "name": "API4: Unrestricted Resource Consumption (No Rate Limit)",
      "severity": 6,
      "endpoint": "/workshop/api/shop/orders",
      "description": "Отсутствует ограничение частоты запросов (10 rapid requests).",
      "evidence": "10 rapid requests returned 200 OK"
    },
    {
      "vuln_id": "bf5cb237",
      "name": "API8: Security Misconfiguration",
      "severity": 6,
      "endpoint": "/workshop/api/shop/orders",
      "description": "Отсутствуют защитные заголовки: strict-transport-security.",
      "evidence": "{'Server': 'openresty/1.27.1.2', 'Date': 'Wed, 27 May 2026 01:06:19 GMT', 'Content-Type': 'application/json', 'Transfer-Encoding': 'chunked', 'Connect"
    },
    {
      "vuln_id": "fb40500b",
      "name": "API1: Broken Object Level Authorization (BOLA)",
      "severity": 9,
      "endpoint": "/workshop/api/shop/orders/1",
      "description": "Доступ к объекту с ID 1 без проверки владения.",
      "evidence": "{\"order\":{\"id\":1,\"user\":{\"email\":\"adam007@example.com\",\"number\":\"9876895423\"},\"product\":{\"id\":1,\"name\":\"Seat\",\"price\":\"10.00\",\"image_url\":\"images/seat.svg\"},\"quantity\":2,\"status\":\"delivered\",\"transact"
    },
    {
      "vuln_id": "a24de25e",
      "name": "API1: Broken Object Level Authorization (BOLA)",
      "severity": 9,
      "endpoint": "/workshop/api/shop/orders/2",
      "description": "Доступ к объекту с ID 2 без проверки владения.",
      "evidence": "{\"order\":{\"id\":2,\"user\":{\"email\":\"pogba006@example.com\",\"number\":\"9876570006\"},\"product\":{\"id\":1,\"name\":\"Seat\",\"price\":\"10.00\",\"image_url\":\"images/seat.svg\"},\"quantity\":2,\"status\":\"delivered\",\"transac"
    },
    {
      "vuln_id": "4b5d858a",
      "name": "API8: Security Misconfiguration",
      "severity": 6,
      "endpoint": "/workshop/api/shop/orders/{order_id}",
      "description": "Отсутствуют защитные заголовки: strict-transport-security.",
      "evidence": "{'Server': 'openresty/1.27.1.2', 'Date': 'Wed, 27 May 2026 01:06:48 GMT', 'Content-Type': 'text/html; charset=utf-8', 'Transfer-Encoding': 'chunked', "
    },
    {
      "vuln_id": "24159d2a",
      "name": "API1: Broken Object Level Authorization (BOLA)",
      "severity": 9,
      "endpoint": "/workshop/api/shop/orders/1",
      "description": "Доступ к объекту с ID 1 без проверки владения.",
      "evidence": "{\"order\":{\"id\":1,\"user\":{\"email\":\"adam007@example.com\",\"number\":\"9876895423\"},\"product\":{\"id\":1,\"name\":\"Seat\",\"price\":\"10.00\",\"image_url\":\"images/seat.svg\"},\"quantity\":2,\"status\":\"delivered\",\"transact"
    },
    {
      "vuln_id": "c4e2c740",
      "name": "API1: Broken Object Level Authorization (BOLA)",
      "severity": 9,
      "endpoint": "/workshop/api/shop/orders/2",
      "description": "Доступ к объекту с ID 2 без проверки владения.",
      "evidence": "{\"order\":{\"id\":2,\"user\":{\"email\":\"pogba006@example.com\",\"number\":\"9876570006\"},\"product\":{\"id\":1,\"name\":\"Seat\",\"price\":\"10.00\",\"image_url\":\"images/seat.svg\"},\"quantity\":2,\"status\":\"delivered\",\"transac"
    },
    {
      "vuln_id": "ebe59274",
      "name": "API8: Security Misconfiguration",
      "severity": 6,
      "endpoint": "/workshop/api/shop/orders/{order_id}",
      "description": "Отсутствуют защитные заголовки: strict-transport-security.",
      "evidence": "{'Server': 'openresty/1.27.1.2', 'Date': 'Wed, 27 May 2026 01:07:01 GMT', 'Content-Type': 'text/html; charset=utf-8', 'Transfer-Encoding': 'chunked', "
    },
    {
      "vuln_id": "4004fb88",
      "name": "API4: Unrestricted Resource Consumption (No Rate Limit)",
      "severity": 6,
      "endpoint": "/workshop/api/shop/orders/all",
      "description": "Отсутствует ограничение частоты запросов (10 rapid requests).",
      "evidence": "10 rapid requests returned 200 OK"
    },
    {
      "vuln_id": "a644b85a",
      "name": "API8: Security Misconfiguration",
      "severity": 6,
      "endpoint": "/workshop/api/shop/orders/all",
      "description": "Отсутствуют защитные заголовки: strict-transport-security.",
      "evidence": "{'Server': 'openresty/1.27.1.2', 'Date': 'Wed, 27 May 2026 01:07:14 GMT', 'Content-Type': 'application/json', 'Transfer-Encoding': 'chunked', 'Connect"
    },
    {
      "vuln_id": "5dcd6007",
      "name": "API8: Security Misconfiguration",
      "severity": 6,
      "endpoint": "/workshop/api/shop/orders/return_order",
      "description": "Отсутствуют защитные заголовки: strict-transport-security.",
      "evidence": "{'Server': 'openresty/1.27.1.2', 'Date': 'Wed, 27 May 2026 01:07:36 GMT', 'Content-Type': 'text/html; charset=utf-8', 'Transfer-Encoding': 'chunked', "
    },
    {
      "vuln_id": "9eb3e095",
      "name": "API4: Unrestricted Resource Consumption (No Rate Limit)",
      "severity": 6,
      "endpoint": "/workshop/api/shop/apply_coupon",
      "description": "Отсутствует ограничение частоты запросов (10 rapid requests).",
      "evidence": "10 rapid requests returned 200 OK"
    },
    {
      "vuln_id": "b73d324f",
      "name": "API6: Unrestricted Access to Sensitive Business Flows",
      "severity": 8,
      "endpoint": "/workshop/api/shop/apply_coupon",
      "description": "Бизнес-процесс выполнен без обязательной валидации состояния.",
      "evidence": "{\"credit\":165.0,\"message\":\"Coupon successfully applied!\"}"
    },
    {
      "vuln_id": "67322f51",
      "name": "API8: Security Misconfiguration",
      "severity": 6,
      "endpoint": "/workshop/api/shop/apply_coupon",
      "description": "Отсутствуют защитные заголовки: strict-transport-security.",
      "evidence": "{'Server': 'openresty/1.27.1.2', 'Date': 'Wed, 27 May 2026 01:07:45 GMT', 'Content-Type': 'application/json', 'Transfer-Encoding': 'chunked', 'Connect"
    },
    {
      "vuln_id": "359a8929",
      "name": "API4: Unrestricted Resource Consumption (No Rate Limit)",
      "severity": 6,
      "endpoint": "/workshop/api/shop/return_qr_code",
      "description": "Отсутствует ограничение частоты запросов (10 rapid requests).",
      "evidence": "10 rapid requests returned 200 OK"
    },
    {
      "vuln_id": "ac4f67d6",
      "name": "API8: Security Misconfiguration",
      "severity": 6,
      "endpoint": "/workshop/api/shop/return_qr_code",
      "description": "Отсутствуют защитные заголовки: strict-transport-security.",
      "evidence": "{'Server': 'openresty/1.27.1.2', 'Date': 'Wed, 27 May 2026 01:08:14 GMT', 'Content-Type': 'image/png', 'Content-Length': '7189', 'Connection': 'keep-a"
    },
    {
      "vuln_id": "7ffb7d38",
      "name": "API4: Unrestricted Resource Consumption (No Rate Limit)",
      "severity": 6,
      "endpoint": "/workshop/api/management/users/all",
      "description": "Отсутствует ограничение частоты запросов (10 rapid requests).",
      "evidence": "10 rapid requests returned 200 OK"
    },
    {
      "vuln_id": "92c89e60",
      "name": "API5: Broken Function Level Authorization (BFLA)",
      "severity": 9,
      "endpoint": "/workshop/api/management/users/all",
      "description": "Административный эндпоинт доступен для обычного пользователя.",
      "evidence": "{\"users\":[{\"user\":{\"email\":\"adam007@example.com\",\"number\":\"9876895423\"},\"available_credit\":100.0},{\"user\":{\"email\":\"pogba006@example.com\",\"number\":\"9876570006\"},\"available_credit\":100.0},{\"user\":{\"ema"
    },
    {
      "vuln_id": "27090664",
      "name": "API8: Security Misconfiguration",
      "severity": 6,
      "endpoint": "/workshop/api/management/users/all",
      "description": "Отсутствуют защитные заголовки: strict-transport-security.",
      "evidence": "{'Server': 'openresty/1.27.1.2', 'Date': 'Wed, 27 May 2026 01:08:36 GMT', 'Content-Type': 'application/json', 'Transfer-Encoding': 'chunked', 'Connect"
    },
    {
      "vuln_id": "5f8c1e7c",
      "name": "API4: Unrestricted Resource Consumption (No Rate Limit)",
      "severity": 6,
      "endpoint": "/workshop/api/mechanic/",
      "description": "Отсутствует ограничение частоты запросов (10 rapid requests).",
      "evidence": "10 rapid requests returned 200 OK"
    },
    {
      "vuln_id": "0791dd32",
      "name": "API8: Security Misconfiguration",
      "severity": 6,
      "endpoint": "/workshop/api/mechanic/",
      "description": "Отсутствуют защитные заголовки: strict-transport-security.",
      "evidence": "{'Server': 'openresty/1.27.1.2', 'Date': 'Wed, 27 May 2026 01:08:59 GMT', 'Content-Type': 'application/json', 'Transfer-Encoding': 'chunked', 'Connect"
    },
    {
      "vuln_id": "769daf48",
      "name": "API7: Server Side Request Forgery (SSRF)",
      "severity": 9,
      "endpoint": "/workshop/api/merchant/contact_mechanic",
      "description": "Сервер выполнил запрос к внутреннему ресурсу или вернул ошибку сервиса.",
      "evidence": "{\"response_from_mechanic_api\":\"<!DOCTYPE html>\\n<html ng-app=\\\"mailhogApp\\\">\\n  <head>\\n    <title>MailHog</title>\\n    <meta charset=\\\"utf-8\\\">\\n    <meta http-equiv=\\\"X-UA-Compatible\\\" content=\\\"IE="
    },
    {
      "vuln_id": "db96f7a0",
      "name": "API8: Security Misconfiguration",
      "severity": 6,
      "endpoint": "/workshop/api/merchant/contact_mechanic",
      "description": "Отсутствуют защитные заголовки: strict-transport-security.",
      "evidence": "{'Server': 'openresty/1.27.1.2', 'Date': 'Wed, 27 May 2026 01:09:22 GMT', 'Content-Type': 'application/json', 'Transfer-Encoding': 'chunked', 'Connect"
    },
    {
      "vuln_id": "247ac2b6",
      "name": "API10: Unsafe Consumption of APIs",
      "severity": 7,
      "endpoint": "/workshop/api/merchant/contact_mechanic",
      "description": "API раскрывает внутренние ошибки или детали подключения к внешним сервисам.",
      "evidence": "{\"message\":\"Could not connect to mechanic api.\"}"
    },
    {
      "vuln_id": "08419f64",
      "name": "API8: Security Misconfiguration",
      "severity": 6,
      "endpoint": "/workshop/api/mechanic/receive_report",
      "description": "Отсутствуют защитные заголовки: strict-transport-security.",
      "evidence": "{'Server': 'openresty/1.27.1.2', 'Date': 'Wed, 27 May 2026 01:09:32 GMT', 'Content-Type': 'application/json', 'Transfer-Encoding': 'chunked', 'Connect"
    },
    {
      "vuln_id": "95488859",
      "name": "API8: Security Misconfiguration",
      "severity": 6,
      "endpoint": "/workshop/api/mechanic/mechanic_report",
      "description": "Отсутствуют защитные заголовки: strict-transport-security.",
      "evidence": "{'Server': 'openresty/1.27.1.2', 'Date': 'Wed, 27 May 2026 01:09:35 GMT', 'Content-Type': 'text/html; charset=utf-8', 'Transfer-Encoding': 'chunked', "
    },
    {
      "vuln_id": "490bb421",
      "name": "API4: Unrestricted Resource Consumption (No Rate Limit)",
      "severity": 6,
      "endpoint": "/workshop/api/mechanic/service_requests",
      "description": "Отсутствует ограничение частоты запросов (10 rapid requests).",
      "evidence": "10 rapid requests returned 200 OK"
    },
    {
      "vuln_id": "8e3dd3d6",
      "name": "API8: Security Misconfiguration",
      "severity": 6,
      "endpoint": "/workshop/api/mechanic/service_requests",
      "description": "Отсутствуют защитные заголовки: strict-transport-security.",
      "evidence": "{'Server': 'openresty/1.27.1.2', 'Date': 'Wed, 27 May 2026 01:09:37 GMT', 'Content-Type': 'application/json', 'Transfer-Encoding': 'chunked', 'Connect"
    },
    {
      "vuln_id": "7e0ea53f",
      "name": "API8: Security Misconfiguration",
      "severity": 6,
      "endpoint": "/workshop/api/mechanic/signup",
      "description": "Отсутствуют защитные заголовки: strict-transport-security.",
      "evidence": "{'Server': 'openresty/1.27.1.2', 'Date': 'Wed, 27 May 2026 01:10:00 GMT', 'Content-Type': 'application/json', 'Transfer-Encoding': 'chunked', 'Connect"
    }
  ]
}